slopit/__init__.py
slopit/cli.py
slopit/py.typed
slopit/behavioral/__init__.py
slopit/behavioral/base.py
slopit/behavioral/focus.py
slopit/behavioral/keystroke.py
slopit/behavioral/paste.py
slopit/behavioral/timing.py
slopit/dashboard/__init__.py
slopit/dashboard/app.py
slopit/dashboard/config.py
slopit/dashboard/dependencies.py
slopit/dashboard/api/__init__.py
slopit/dashboard/api/analysis.py
slopit/dashboard/api/export.py
slopit/dashboard/api/jatos.py
slopit/dashboard/api/prolific.py
slopit/dashboard/api/sessions.py
slopit/dashboard/api/trials.py
slopit/dashboard/integrations/__init__.py
slopit/dashboard/integrations/jatos.py
slopit/dashboard/integrations/prolific.py
slopit/dashboard/services/__init__.py
slopit/dashboard/services/analysis_service.py
slopit/dashboard/services/export_service.py
slopit/dashboard/services/session_service.py
slopit/dashboard/services/storage_service.py
slopit/dashboard/static/.gitkeep
slopit/dashboard/static/index.html
slopit/dashboard/static/slopit-dashboard-wc.css
slopit/dashboard/static/slopit-dashboard-wc.js
slopit/dashboard/websocket/__init__.py
slopit/dashboard/websocket/events.py
slopit/dashboard/websocket/handlers.py
slopit/dashboard/websocket/manager.py
slopit/io/__init__.py
slopit/io/base.py
slopit/io/jatos.py
slopit/io/native.py
slopit/pipeline/__init__.py
slopit/pipeline/aggregation.py
slopit/pipeline/pipeline.py
slopit/pipeline/reporting.py
slopit/schemas/__init__.py
slopit/schemas/analysis.py
slopit/schemas/behavioral.py
slopit/schemas/flags.py
slopit/schemas/session.py
slopit/schemas/types.py
slopit-0.1.0.dist-info/METADATA
slopit-0.1.0.dist-info/WHEEL
slopit-0.1.0.dist-info/entry_points.txt
slopit-0.1.0.dist-info/RECORD
