Metadata-Version: 2.4
Name: slopit
Version: 0.1.0
Summary: AI response detection toolkit for crowdsourced behavioral research
Project-URL: Homepage, https://github.com/slopit/slopit
Project-URL: Documentation, https://slopit.github.io
Project-URL: Repository, https://github.com/slopit/slopit
Project-URL: Issues, https://github.com/slopit/slopit/issues
Author-email: Aaron Steven White <aaron.white@rochester.edu>
License-Expression: MIT
Keywords: ai-detection,behavioral-research,crowdsourcing,keystroke-dynamics,stylometry
Classifier: Development Status :: 3 - Alpha
Classifier: Intended Audience :: Science/Research
Classifier: License :: OSI Approved :: MIT License
Classifier: Programming Language :: Python :: 3
Classifier: Programming Language :: Python :: 3.13
Classifier: Topic :: Scientific/Engineering
Classifier: Typing :: Typed
Requires-Python: >=3.13
Requires-Dist: click>=8.1
Requires-Dist: numpy>=2.0
Requires-Dist: pandas>=2.2
Requires-Dist: pydantic>=2.10
Requires-Dist: rich>=13.0
Requires-Dist: scikit-learn>=1.5
Requires-Dist: sentence-transformers>=3.0
Requires-Dist: spacy>=3.8
Provides-Extra: dashboard
Requires-Dist: fastapi>=0.115; extra == 'dashboard'
Requires-Dist: httpx>=0.27; extra == 'dashboard'
Requires-Dist: python-multipart>=0.0.9; extra == 'dashboard'
Requires-Dist: uvicorn>=0.32; extra == 'dashboard'
Requires-Dist: websockets>=12.0; extra == 'dashboard'
Provides-Extra: dev
Requires-Dist: hypothesis>=6.120; extra == 'dev'
Requires-Dist: mkdocs-material>=9.5; extra == 'dev'
Requires-Dist: mkdocstrings[python]>=0.27; extra == 'dev'
Requires-Dist: pyright>=1.1.390; extra == 'dev'
Requires-Dist: pytest-asyncio>=0.24; extra == 'dev'
Requires-Dist: pytest-cov>=6.0; extra == 'dev'
Requires-Dist: pytest>=8.3; extra == 'dev'
Requires-Dist: ruff>=0.8; extra == 'dev'
Provides-Extra: docs
Requires-Dist: mkdocs-material>=9.5.0; extra == 'docs'
Requires-Dist: mkdocs>=1.6.0; extra == 'docs'
Requires-Dist: mkdocstrings[python]>=0.27.0; extra == 'docs'
Provides-Extra: llm
Requires-Dist: torch>=2.5; extra == 'llm'
Requires-Dist: transformers>=4.47; extra == 'llm'
Provides-Extra: server
Requires-Dist: fastapi>=0.115; extra == 'server'
Requires-Dist: uvicorn>=0.32; extra == 'server'
